{
    "alternate":1,
    "reality":1,
    "drowning":1,
    "swimming":1,
    "stressful":1,
    "waters":1,
    "relief":1,
    "prolly":1,
    "sunshine":1,
    "looked":1,
    "grey":1,
    "skies":1,
    "drifting":1,
    "pay":1,
    "cost":1,
    "apostrophes":1,
    "means":1,
    "taking":1,
    "ignition":1,
    "driven":1,
    "sittin":1,
    "whitney":1,
    "mission":1,
    "putting":1,
    "richer":1,
    "mama":1,
    "pa":1,
    "sounded":1,
    "concert":1,
    "monster":1,
    "truck":1,
    "falling":1,
    "throwing":1,
    "system":1,
    "bringing":1,
    "iffy":1,
    "fifty":1,
    "percent":1,
    "dealing":1,
    "depressed":1,
    "obsessed":1,
    "jacuzzis":1,
    "hitting":1,
    "jets":1,
    "showing":1,
    "givin":1,
    "sex":1,
    "outline":1,
    "victim":1,
    "pride":1,
    "step":1,
    "aside":1,
    "yep":1,
    "grounded":1,
    "push":1,
    "whips":1,
    "mountains":1,
    "blue":1,
    "fountains":1,
    "surroundings":1,
    "going":1,
    "colder":1,
    "flowin":1,
    "truly":1,
    "beyond":1,
    "drugs":1,
    "shuttle":1,
    "elon":1,
    "sing":1,
    "céline":1,
    "dion":1,
    "lotta":1,
    "exit":1,
    "ticking":1,
    "highly":1,
    "pilot":1,
    "somethin":1,
    "witness":1,
    "understand":1,
    "theyll":1,
    "worked":1,
    "clue":1,
    "bar":1,
    "par":1,
    "parlay":1,
    "range":1,
    "yard":1,
    "pray":1,
    "promise":1,
    "nobodyd":1,
    "hungry":1,
    "dirt":1,
    "brain":1,
    "heads":1,
    "turnin":1,
    "hurricane":1,
    "swervin":1,
    "outta":1,
    "shade":1,
    "frame":1,
    "30":1,
    "thou":1,
    "ah":1,
    "collected":1,
    "expected":1,
    "argue":1,
    "death":1,
    "cards":1,
    "table":1,
    "swallow":1,
    "borrowed":1,
    "fence":1,
    "goin":1,
    "bet":1,
    "drown":1,
    "shore":1,
    "weekend":1,
    "tuesday":1,
    "days":1,
    "dusse":1,
    "kool":1,
    "aid":1,
    "j":1,
    "anyways":1,
    "purer":1,
    "alkaline":1,
    "bitch":1,
    "album":1,
    "withdrawal":1,
    "flow":1,
    "air":1,
    "unfold":1,
    "sat":1,
    "watched":1,
    "knowin":1,
    "clocks":1,
    "bare":1,
    "bargain":1,
    "important":1,
    "sorta":1,
    "order":1,
    "climbing":1,
    "height":1,
    "september":1,
    "medicine":1,
    "melt":1,
    "treatin":1,
    "reading":1,
    "lovely":1,
    "family":1,
    "tree":1,
    "drove":1,
    "speedin":1,
    "lettin":1,
    "lil":1,
    "kay":1,
    "quickly":1,
    "disc":1,
    "upload":1,
    "spinnin":1,
    "travel":1,
    "unknown":1,
    "fucked":1,
    "45s":1,
    "safer":1,
    "outside":1,
    "liquored":1,
    "mornings":1,
    "bought":1,
    "fist":1,
    "spent":1,
    "notice":1,
    "talkin":1,
    "wander":1,
    "motives":1,
    "wonder":1,
    "supposed":1,
    "beside":1,
    "wind":1,
    "great":1,
    "sidewalk":1,
    "picked":1,
    "familiar":1,
    "realer":1,
    "thoughts":1,
    "fast":1,
    "clock":1,
    "seeds":1,
    "flower":1,
    "normal":1,
    "silence":1,
    "growin":1,
    "123":1,
    "hand":1,
    "problem":1,
    "help":1,
    "serve":1,
    "universe":1,
    "lucifer":1,
    "include":1,
    "company":1,
    "follow":1,
    "owed":1,
    "bucks":1,
    "temper":1,
    "meets":1,
    "swimmin":1,
    "deeper":1,
    "thought":1,
    "keepin":1,
    "box":1,
    "level":1,
    "needin":1,
    "whether":1,
    "knockin":1,
    "maintain":1,
    "stayin":1,
    "lighter":1,
    "touchin":1,
    "dead":1,
    "color":1,
    "size":1,
    "beneficial":1,
    "lovin":1,
    "whistle":1,
    "wakin":1,
    "open":1,
    "closer":1,
    "shy":1,
    "flickerin":1,
    "hittin":1,
    "switches":1,
    "bullshittin":1,
    "stand":1,
    "delay":1,
    "flip":1,
    "grip":1,
    "smell":1,
    "burn":1,
    "castle":1,
    "grand":1,
    "hassle":1,
    "besides":1,
    "castles":1,
    "sand":1,
    "sea":1,
    "maze":1,
    "mall":1,
    "dunk":1,
    "knows":1,
    "whoever":1,
    "rich":1,
    "lonely":1,
    "five":1,
    "star":1,
    "rush":1,
    "hush":1,
    "attitude":1,
    "playing":1,
    "moves":1,
    "speeds":1,
    "beat":1,
    "control":1,
    "freak":1,
    "veins":1,
    "freezing":1,
    "snow":1,
    "season":1,
    "case":1,
    "waist":1,
    "stroke":1,
    "pga":1,
    "drawing":1,
    "shapes":1,
    "tomorrow":1,
    "may":1,
    "corner":1,
    "babe":1,
    "somewhere":1,
    "reaching":1,
    "ten":1,
    "wrote":1,
    "fingers":1,
    "slippin":1,
    "motherfuckin":1,
    "instant":1,
    "mediocre":1,
    "staring":1,
    "posters":1,
    "dreams":1,
    "believe":1,
    "fool":1,
    "beings":1,
    "glued":1,
    "shoes":1,
    "consumed":1,
    "suns":1,
    "tired":1,
    "spare":1,
    "second":1,
    "checkin":1,
    "basic":1,
    "entertainment":1,
    "single":1,
    "kid":1,
    "imagination":1,
    "improve":1,
    "wastin":1,
    "hatin":1,
    "lacin":1,
    "sneakers":1,
    "running":1,
    "patience":1,
    "famous":1,
    "wild":1,
    "dangerous":1,
    "dollars":1,
    "actin":1,
    "statements":1,
    "pocket":1,
    "aces":1,
    "invasions":1,
    "vacations":1,
    "wave":1,
    "wavy":1,
    "boy":1,
    "savings":1,
    "amazing":1,
    "pavement":1,
    "whatever":1,
    "people":1,
    "almost":1,
    "missed":1,
    "last":1,
    "coughin":1,
    "weed":1,
    "cute":1,
    "phone":1,
    "sleep":1,
    "weird":1,
    "switch":1,
    "gears":1,
    "lips":1,
    "kiss":1,
    "touch":1,
    "wheel":1,
    "thank":1,
    "favorite":1,
    "pop":1,
    "stage":1,
    "capitol":1,
    "proper":1,
    "ga":1,
    "di":1,
    "limba":1,
    "den":1,
    "vampire":1,
    "stabbin":1,
    "penny":1,
    "collab":1,
    "rude":1,
    "culture":1,
    "mon":1,
    "praise":1,
    "almighty":1,
    "trenton":1,
    "rankin":1,
    "stamina":1,
    "super":1,
    "hero":1,
    "cape":1,
    "catching":1,
    "guys":1,
    "underwater":1,
    "shower":1,
    "baptised":1,
    "cuts":1,
    "bones":1,
    "black":1,
    "million":1,
    "rap":1,
    "yall":1,
    "floor":1,
    "goat":1,
    "backflip":1,
    "rope":1,
    "hook":1,
    "post":1,
    "girl":1,
    "clutch":1,
    "choke":1,
    "calling":1,
    "quits":1,
    "build":1,
    "bricks":1,
    "liquor":1,
    "cup":1,
    "woke":1,
    "morning":1,
    "bright":1,
    "idea":1,
    "exist":1,
    "hundredtwenty":1,
    "whip":1,
    "driveway":1,
    "shots":1,
    "limit":1,
    "stakes":1,
    "card":1,
    "fish":1,
    "quick":1,
    "f":1,
    "uh":1,
    "jumping":1,
    "womb":1,
    "wearing":1,
    "polo":1,
    "school":1,
    "lone":1,
    "wolf":1,
    "solo":1,
    "kick":1,
    "side":1,
    "pulling":1,
    "dick":1,
    "demand":1,
    "share":1,
    "clear":1,
    "vet":1,
    "twentyfive":1,
    "years":1,
    "less":1,
    "stress":1,
    "fate":1,
    "waitin":1,
    "eric":1,
    "swim":1,
    "dim":1,
    "sin":1,
    "breathe":1,
    "easy":1,
    "beamin":1,
    "team":1,
    "bout":1,
    "ice":1,
    "simpler":1,
    "route":1,
    "instead":1,
    "havin":1,
    "demons":1,
    "dribble":1,
    "bounce":1,
    "party":1,
    "kickin":1,
    "buy":1,
    "ugly":1,
    "yay":1,
    "muddy":1,
    "ask":1,
    "smilin":1,
    "alive":1,
    "struck":1,
    "swingin":1,
    "finish":1,
    "diggin":1,
    "hole":1,
    "bury":1,
    "soul":1,
    "weight":1,
    "songs":1,
    "scared":1,
    "hurry":1,
    "worry":1,
    "730":1,
    "low":1,
    "unturned":1,
    "stones":1,
    "pro":1,
    "job":1,
    "believin":1,
    "panic":1,
    "sound":1,
    "alarm":1,
    "um":1,
    "red":1,
    "headaches":1,
    "alcoholics":1,
    "wallet":1,
    "dreamin":1,
    "built":1,
    "promised":1,
    "bring":1,
    "flavor":1,
    "seasons":1,
    "summer":1,
    "grass":1,
    "greener":1,
    "studies":1,
    "applause":1,
    "countin":1,
    "boss":1,
    "exhausting":1,
    "later":1,
    "posted":1,
    "ok":1,
    "topic":1,
    "narcissism":1,
    "narcotics":1,
    "special":1,
    "delivery":1,
    "endless":1,
    "artillery":1,
    "enterprise":1,
    "lives":1,
    "die":1,
    "heaven":1,
    "nevermind":1,
    "mention":1,
    "wetter":1,
    "dry":1,
    "clementine":1,
    "peelin":1,
    "57":1,
    "cept":1,
    "75":1,
    "cross":1,
    "planets":1,
    "interstellar":1,
    "jackson":1,
    "packed":1,
    "action":1,
    "happening":1,
    "relaxing":1,
    "kicking":1,
    "exactly":1,
    "satisfaction":1,
    "circle":1,
    "regrets":2,
    "text":2,
    "neighbors":2,
    "theyre":2,
    "strangers":2,
    "friends":2,
    "anything":2,
    "things":2,
    "id":2,
    "rain":2,
    "thrown":2,
    "line":2,
    "driving":2,
    "missing":2,
    "signs":2,
    "pretty":2,
    "listenin":2,
    "whippin":2,
    "man":2,
    "figure":2,
    "shoulders":2,
    "bigger":2,
    "smaller":2,
    "crazy":2,
    "mercedes":2,
    "begun":2,
    "king":2,
    "power":2,
    "spring":2,
    "everyone":2,
    "hundred":2,
    "forget":2,
    "used":2,
    "respect":2,
    "lyin":2,
    "truth":2,
    "motherfucker":2,
    "seem":2,
    "waste":2,
    "whole":2,
    "left":2,
    "talking":2,
    "business":2,
    "set":2,
    "far":2,
    "probably":2,
    "save":2,
    "funny":2,
    "throwin":2,
    "name":2,
    "picture":2,
    "cut":2,
    "worth":2,
    "holdin":2,
    "chest":2,
    "callin":2,
    "often":2,
    "addin":2,
    "ground":2,
    "treading":2,
    "workin":2,
    "else":2,
    "stuck":2,
    "coming":2,
    "movin":2,
    "car":2,
    "thing":2,
    "together":2,
    "tall":2,
    "hot":2,
    "elsewhere":2,
    "self":2,
    "must":2,
    "lights":2,
    "somebody":2,
    "thinking":2,
    "chillin":2,
    "beautiful":2,
    "connect":2,
    "war":2,
    "bone":2,
    "roses":2,
    "broken":2,
    "next":2,
    "face":2,
    "slip":2,
    "motif":2,
    "felt":2,
    "count":2,
    "gamble":2,
    "shinin":2,
    "horizon":2,
    "wider":2,
    "grow":2,
    "broke":2,
    "hear":2,
    "human":2,
    "fuckin":2,
    "real":2,
    "strong":2,
    "wrong":2,
    "free":2,
    "blow":2,
    "wait":2,
    "shoot":2,
    "extras":2,
    "hotel":2,
    "try":2,
    "peace":2,
    "old":2,
    "smoke":2,
    "glow":2,
    "nine":2,
    "times":2,
    "win":2,
    "house":2,
    "faded":2,
    "mad":2,
    "hm":2,
    "goddamn":2,
    "work":2,
    "harder":2,
    "alone":2,
    "dancehall":2,
    "kill":2,
    "wit":2,
    "dutty":2,
    "judger":2,
    "de":2,
    "pussy":2,
    "dear":2,
    "took":2,
    "winter":2,
    "sometimes":2,
    "big":2,
    "mhmm":2,
    "carry":2,
    "palm":2,
    "reach":2,
    "pockets":2,
    "gather":2,
    "standing":2,
    "woahoh":2,
    "ropes":2,
    "send":3,
    "living":3,
    "spend":3,
    "hell":3,
    "wish":3,
    "nice":3,
    "away":3,
    "lifted":3,
    "paid":3,
    "city":3,
    "said":3,
    "live":3,
    "new":3,
    "without":3,
    "another":3,
    "minute":3,
    "superficial":3,
    "sentimental":3,
    "juice":3,
    "breeze":3,
    "hol":3,
    "show":3,
    "space":3,
    "wake":3,
    "catch":3,
    "damn":3,
    "plan":3,
    "already":3,
    "land":3,
    "homies":3,
    "worried":3,
    "plus":3,
    "surface":3,
    "makin":3,
    "calm":3,
    "heart":3,
    "livin":3,
    "miss":3,
    "start":3,
    "nothin":3,
    "spin":3,
    "pick":3,
    "seen":3,
    "switched":3,
    "zone":3,
    "spending":3,
    "hitchhikin":3,
    "surprise":3,
    "hiding":3,
    "gliding":3,
    "roll":3,
    "fall":3,
    "trust":3,
    "losin":3,
    "round":3,
    "comin":3,
    "walls":3,
    "ear":3,
    "jump":3,
    "ever":3,
    "meet":3,
    "ball":3,
    "drop":3,
    "bit":3,
    "gone":3,
    "sky":3,
    "shot":3,
    "flight":3,
    "trip":3,
    "lose":3,
    "maybe":3,
    "building":3,
    "us":3,
    "young":3,
    "song":3,
    "full":3,
    "lookin":3,
    "planet":3,
    "speak":3,
    "language":3,
    "occasion":3,
    "recognize":3,
    "faces":3,
    "spacious":3,
    "sit":3,
    "takin":3,
    "busy":3,
    "otherwise":3,
    "couple":3,
    "told":4,
    "gets":4,
    "better":4,
    "complain":4,
    "strange":4,
    "game":4,
    "closed":4,
    "please":4,
    "hold":4,
    "hurt":4,
    "feelings":4,
    "yes":4,
    "think":4,
    "freaks":4,
    "sun":4,
    "miles":4,
    "swear":4,
    "care":4,
    "tryna":4,
    "matter":4,
    "runnin":4,
    "started":4,
    "though":4,
    "nights":4,
    "remember":4,
    "one":4,
    "gonna":4,
    "slow":4,
    "watch":4,
    "many":4,
    "hey":4,
    "weather":4,
    "comes":4,
    "fallin":4,
    "cold":4,
    "small":4,
    "god":4,
    "basement":4,
    "every":4,
    "conversation":4,
    "expect":4,
    "rescued":4,
    "hands":4,
    "nowadays":4,
    "ease":4,
    "cry":4,
    "angels":4,
    "sposed":4,
    "askin":4,
    "stay":4,
    "2009":4,
    "ill":5,
    "myself":5,
    "sayin":5,
    "change":5,
    "missin":5,
    "mine":5,
    "bullshit":5,
    "pull":5,
    "enough":5,
    "feelin":5,
    "slide":5,
    "crib":5,
    "leave":5,
    "theres":5,
    "gon":5,
    "ride":5,
    "fine":5,
    "shine":5,
    "put":5,
    "kinda":5,
    "call":5,
    "lets":5,
    "feels":5,
    "guess":5,
    "somehow":5,
    "night":5,
    "along":5,
    "forever":6,
    "trippin":6,
    "much":6,
    "water":6,
    "baby":6,
    "long":6,
    "move":6,
    "use":6,
    "hit":6,
    "might":6,
    "ooh":6,
    "close":6,
    "breath":6,
    "feet":6,
    "stop":6,
    "door":6,
    "feeling":6,
    "alright":6,
    "bad":6,
    "wings":6,
    "takes":6,
    "top":6,
    "lot":6,
    "lie":6,
    "spaceship":6,
    "hmm":6,
    "longer":6,
    "lost":6,
    "behind":6,
    "everything":7,
    "turn":7,
    "make":7,
    "ima":7,
    "money":7,
    "em":7,
    "perfect":7,
    "buggin":7,
    "hate":7,
    "play":7,
    "wall":7,
    "life":7,
    "hope":7,
    "light":7,
    "lines":7,
    "rather":7,
    "want":8,
    "give":8,
    "something":8,
    "cool":8,
    "late":8,
    "till":8,
    "whoa":8,
    "town":8,
    "fuel":8,
    "different":9,
    "cant":9,
    "gettin":9,
    "around":9,
    "let":9,
    "jet":9,
    "came":9,
    "hard":9,
    "still":9,
    "oh":9,
    "clouds":9,
    "home":9,
    "nobody":9,
    "head":10,
    "day":10,
    "shame":10,
    "eyes":10,
    "ive":10,
    "made":10,
    "say":10,
    "good":10,
    "break":10,
    "waiting":10,
    "today":10,
    "look":11,
    "even":11,
    "okay":11,
    "everybody":11,
    "world":11,
    "fly":11,
    "find":11,
    "run":11,
    "inside":12,
    "love":12,
    "whats":12,
    "cause":12,
    "oblivion":12,
    "little":13,
    "always":13,
    "getting":13,
    "see":13,
    "high":13,
    "nothing":13,
    "come":13,
    "feel":14,
    "back":14,
    "goes":14,
    "got":15,
    "gotta":15,
    "right":16,
    "fuck":16,
    "take":16,
    "could":17,
    "tell":18,
    "go":18,
    "really":19,
    "way":21,
    "mind":21,
    "thats":23,
    "wanna":23,
    "time":25,
    "keep":25,
    "shit":27,
    "til":27,
    "need":29,
    "well":30,
    "never":32,
    "get":36,
    "no":55,
    "da":58,
    "aint":60,
    "know":61,
    "you":158,
    "yeah":189,
    "i":345
 }