{
    "serenity":1,
    "peace":1,
    "paris":1,
    "parents":1,
    "send":1,
    "oppression":1,
    "blessings":1,
    "whyd":1,
    "persecute":1,
    "weak":1,
    "makes":1,
    "strong":1,
    "save":1,
    "strength":1,
    "wrongs":1,
    "alright":1,
    "care":1,
    "child":1,
    "longer":1,
    "afraid":1,
    "shield":1,
    "judge":1,
    "foot":1,
    "devils":1,
    "drifted":1,
    "pangaea":1,
    "chatham":1,
    "zambia":1,
    "demons":1,
    "pam":1,
    "gina":1,
    "arthur":1,
    "anteater":1,
    "wap":1,
    "snap":1,
    "photos":1,
    "familia":1,
    "sia":1,
    "lyrics":1,
    "spirit":1,
    "braille":1,
    "tubman":1,
    "underground":1,
    "trail":1,
    "sunday":1,
    "fail":1,
    "chance":1,
    "three":1,
    "hear":1,
    "sell":1,
    "snatch":1,
    "bars":1,
    "gosh":1,
    "darn":1,
    "tweet":1,
    "glory":1,
    "sure":1,
    "raincoats":1,
    "rainbow":1,
    "intro":1,
    "fun":1,
    "pillar":1,
    "salt":1,
    "theyll":1,
    "flip":1,
    "script":1,
    "wesley":1,
    "spike":1,
    "mess":1,
    "chano":1,
    "79th":1,
    "prayer":1,
    "prayers":1,
    "messed":1,
    "theyve":1,
    "metro":1,
    "shoot":1,
    "model":1,
    "bleached":1,
    "bleach":1,
    "tshirt":1,
    "tribeca":1,
    "youuh":1,
    "remind":1,
    "owe":1,
    "dreamed":1,
    "cash":1,
    "market":1,
    "divorced":1,
    "drops":1,
    "pops":1,
    "momma":1,
    "pass":1,
    "fast":1,
    "jaw":1,
    "ill":1,
    "hitting":1,
    "licks":1,
    "bando":1,
    "looks":1,
    "montana":1,
    "killers":1,
    "hammers":1,
    "pockets":1,
    "swole":1,
    "danny":1,
    "selling":1,
    "bar":1,
    "macho":1,
    "randy":1,
    "choppa":1,
    "oscar":1,
    "pull":1,
    "ya":1,
    "panty":1,
    "killas":1,
    "sipping":1,
    "versace":1,
    "desiigner":1,
    "bunch":1,
    "lavish":1,
    "clappin":1,
    "pullin":1,
    "ship":1,
    "plenty":1,
    "bugatti":1,
    "killing":1,
    "camera":1,
    "bind":1,
    "stretch":1,
    "kinda":1,
    "swizz":1,
    "southside":1,
    "taylor":1,
    "sex":1,
    "girls":1,
    "nameless":1,
    "fresh":1,
    "mr":1,
    "puerto":1,
    "rican":1,
    "parade":1,
    "floatin":1,
    "benz":1,
    "marina":1,
    "del":1,
    "rey":1,
    "coastin":1,
    "estate":1,
    "month":1,
    "helped":1,
    "payment":1,
    "personal":1,
    "debt":1,
    "woke":1,
    "felt":1,
    "vibe":1,
    "lighters":1,
    "eh":1,
    "bought":1,
    "roley":1,
    "rottweiler":1,
    "fame":1,
    "wilder":1,
    "saying":1,
    "genius":1,
    "borrow":1,
    "motto":1,
    "bother":1,
    "gossiping":1,
    "nopussygetting":1,
    "bloggers":1,
    "fashion":1,
    "gotham":1,
    "costume":1,
    "petas":1,
    "jacket":1,
    "possum":1,
    "awesome":1,
    "austin":1,
    "slave":1,
    "fabric":1,
    "picking":1,
    "cotton":1,
    "hov":1,
    "jordan":1,
    "rodman":1,
    "oprah":1,
    "testimony":1,
    "heart":1,
    "bone":1,
    "body":1,
    "wondering":1,
    "reach":1,
    "hand":1,
    "guide":1,
    "blue":1,
    "door":1,
    "understands":1,
    "arms":1,
    "wide":1,
    "accepting":1,
    "accepted":1,
    "joy":1,
    "sometimes":1,
    "wishin":1,
    "gopro":1,
    "slomo":1,
    "amateur":1,
    "video":1,
    "pro":1,
    "21":1,
    "grammys":1,
    "superstar":1,
    "jacksons":1,
    "action":1,
    "farrakhan":1,
    "marathon":1,
    "shift":1,
    "paradigm":1,
    "bust":1,
    "coachs":1,
    "diddy":1,
    "idiot":1,
    "two":1,
    "lit":1,
    "advice":1,
    "bridget":1,
    "fruit":1,
    "islam":1,
    "trenches":1,
    "yeezus":1,
    "christian":1,
    "spent":1,
    "christians":1,
    "religious":1,
    "breathin":1,
    "past":1,
    "blac":1,
    "chyna":1,
    "rob":1,
    "weight":1,
    "trainer":1,
    "overate":1,
    "vacay":1,
    "kick":1,
    "boss":1,
    "six":1,
    "pack":1,
    "rip":1,
    "aye":1,
    "close":1,
    "things":1,
    "tweaking":1,
    "dig":1,
    "cars":1,
    "tits":1,
    "suck":1,
    "asked":1,
    "twice":1,
    "price":1,
    "boosie":1,
    "wipe":1,
    "woozy":1,
    "motherfuckin":1,
    "dinner":1,
    "table":1,
    "vogue":1,
    "level":1,
    "smack":1,
    "bathroom":1,
    "fucking":1,
    "loud":1,
    "sing":1,
    "chi":1,
    "pie":1,
    "rolls":1,
    "killer":1,
    "straight":1,
    "goals":1,
    "mood":1,
    "rude":1,
    "spaz":1,
    "sweet":1,
    "meet":1,
    "invented":1,
    "polo":1,
    "loves":1,
    "hahaha":1,
    "step":1,
    "talkin":1,
    "scared":1,
    "fistfight":1,
    "grabbin":1,
    "itll":1,
    "fit":1,
    "shine":1,
    "shade":1,
    "bird":1,
    "cage":1,
    "waiting":1,
    "lady":1,
    "jeopardize":1,
    "hoes":1,
    "limits":1,
    "given":1,
    "willing":1,
    "mission":1,
    "vision":1,
    "pour":1,
    "seen":1,
    "crazier":1,
    "lexapro":1,
    "mexico":1,
    "episode":1,
    "code":1,
    "test":1,
    "selfcontrol":1,
    "raising":1,
    "voice":1,
    "especially":1,
    "giuseppe":1,
    "indian":1,
    "veil":1,
    "cares":1,
    "lifes":1,
    "bodys":1,
    "jealous":1,
    "smile":1,
    "switched":1,
    "number":1,
    "bothered":1,
    "havin":1,
    "angle":1,
    "deadbeat":1,
    "reunions":1,
    "church":1,
    "drinkin":1,
    "communion":1,
    "spillin":1,
    "wine":1,
    "tux":1,
    "ruined":1,
    "bottom":1,
    "blamin":1,
    "phone":1,
    "remembered":1,
    "birthday":1,
    "hurry":1,
    "gametime":1,
    "facetime":1,
    "busy":1,
    "jr":1,
    "kid":1,
    "showed":1,
    "yams":1,
    "maybe":1,
    "15":1,
    "minutes":1,
    "sister":1,
    "merry":1,
    "christmas":1,
    "deal":1,
    "defendin":1,
    "spoke":1,
    "centuries":1,
    "enemy":1,
    "pretend":1,
    "lookin":1,
    "fall":1,
    "callin":1,
    "question":1,
    "frontin":1,
    "great":1,
    "somethin":1,
    "immediate":1,
    "extended":1,
    "argument":1,
    "mediall":1,
    "extend":1,
    "250":1,
    "thousand":1,
    "needs":1,
    "hennessey":1,
    "fool":1,
    "everythings":1,
    "wings":1,
    "melt":1,
    "burned":1,
    "heartache":1,
    "drawn":1,
    "warm":1,
    "unseasoned":1,
    "gaze":1,
    "jesus":1,
    "tea":1,
    "sip":1,
    "slippery":1,
    "trippin":1,
    "sippin":1,
    "yo":1,
    "tried":1,
    "advantage":1,
    "fridge":1,
    "sandwich":1,
    "clubbin":1,
    "thuggin":1,
    "hustlin":1,
    "husband":1,
    "hella":1,
    "thugs":1,
    "fore":1,
    "rings":1,
    "ring":1,
    "burn":1,
    "cave":1,
    "blackened":1,
    "dark":1,
    "fleshed":1,
    "heat":1,
    "cooled":1,
    "cool":1,
    "precious":1,
    "checking":1,
    "support":1,
    "dude":1,
    "anyway":1,
    "goes":1,
    "official":1,
    "hollering":1,
    "tsunami":1,
    "joint":1,
    "ahh":1,
    "honor":1,
    "comin":1,
    "alone":1,
    "renovations":1,
    "says":1,
    "recent":1,
    "assessin":1,
    "damages":1,
    "checkin":1,
    "mediatakeout":1,
    "drunk":1,
    "blurry":1,
    "fake":1,
    "veggies":1,
    "eggs":1,
    "gym":1,
    "chest":1,
    "legs":1,
    "yep":1,
    "smoothie":1,
    "wifey":1,
    "switch":1,
    "zone":1,
    "rappin":1,
    "producer":1,
    "trying":1,
    "flows":1,
    "nervous":1,
    "victoria":1,
    "secret":1,
    "pictured":1,
    "clothes":1,
    "expedition":1,
    "eddie":1,
    "bauer":1,
    "edition":1,
    "winter":1,
    "tires":1,
    "december":1,
    "private":1,
    "popeyes":1,
    "pretendin":1,
    "beginnin":1,
    "endin":1,
    "hot":1,
    "hurr":1,
    "room":1,
    "stars":1,
    "omelet":1,
    "5":1,
    "realize":1,
    "doubletree":1,
    "aria":1,
    "waffle":1,
    "western":1,
    "union":1,
    "prob":1,
    "college":1,
    "complainin":1,
    "suckin":1,
    "blowjobs":1,
    "remains":1,
    "unsaid":1,
    "los":1,
    "angeles":1,
    "bans":1,
    "sheets":1,
    "orange":1,
    "spray":1,
    "tan":1,
    "soft":1,
    "porn":1,
    "kman":1,
    "sprinter":1,
    "grape":1,
    "van":1,
    "uhm":1,
    "cutie":1,
    "bougie":1,
    "erykah":1,
    "badu":1,
    "repertoire":1,
    "wrestler":1,
    "ropes":1,
    "connect":1,
    "dots":1,
    "country":1,
    "cook":1,
    "red":1,
    "beans":1,
    "rice":1,
    "dennys":1,
    "4":1,
    "spoil":1,
    "appetite":1,
    "liquor":1,
    "pouring":1,
    "swarming":1,
    "section":1,
    "erection":1,
    "smoke":1,
    "direction":1,
    "pedestrians":1,
    "singers":1,
    "lesbians":1,
    "rappers":1,
    "managers":1,
    "music":1,
    "iphone":1,
    "cameras":1,
    "unanimous":1,
    "damaging":1,
    "holding":1,
    "exclusive":1,
    "rights":1,
    "flew":1,
    "bag":1,
    "divide":1,
    "yam":1,
    "equate":1,
    "math":1,
    "add":1,
    "making":1,
    "alist":1,
    "rapper":1,
    "alphabet":1,
    "backwards":1,
    "dealing":1,
    "malpractice":1,
    "kill":1,
    "confidence":1,
    "nerd":1,
    "condom":1,
    "ladies":1,
    "nam":1,
    "myoho":1,
    "renge":1,
    "kyo":1,
    "words":1,
    "lyrical":1,
    "spiritual":1,
    "miracles":1,
    "buddhist":1,
    "monks":1,
    "captain":1,
    "crunch":1,
    "cereal":1,
    "mercy":1,
    "thou":1,
    "five":1,
    "buddies":1,
    "herded":1,
    "bottle":1,
    "opportunity":1,
    "proper":1,
    "top":1,
    "breast":1,
    "cheek":1,
    "pop":1,
    "community":1,
    "uni":1,
    "fee":1,
    "walk":1,
    "ease":1,
    "units":1,
    "consumer":1,
    "shoe":1,
    "released":1,
    "kicking":1,
    "gratuity":1,
    "g":1,
    "k":1,
    "lamar":1,
    "kind":1,
    "dumb":1,
    "poet":1,
    "lames":1,
    "rookie":1,
    "instagram":1,
    "promote":1,
    "friday":1,
    "breakneck":1,
    "speeds":1,
    "passenger":1,
    "seat":1,
    "pretty":1,
    "base":1,
    "backpack":1,
    "taste":1,
    "buds":1,
    "vuitton":1,
    "stubs":1,
    "become":1,
    "strippers":1,
    "invited":1,
    "hired":1,
    "fired":1,
    "uninspired":1,
    "lauryn":1,
    "hill":1,
    "retired":1,
    "preach":1,
    "choir":1,
    "rumor":1,
    "legendary":1,
    "lewinsky":1,
    "secretaries":1,
    "babies":1,
    "use":1,
    "meal":1,
    "knowing":1,
    "disconnect":1,
    "generation":1,
    "victims":1,
    "fault":1,
    "amber":1,
    "happens":1,
    "philly":1,
    "regularly":1,
    "scheduled":1,
    "programmin":1,
    "content":1,
    "slow":1,
    "worry":1,
    "ones":1,
    "barricades":1,
    "paranoid":1,
    "psychiatrist":1,
    "inspired":1,
    "played":1,
    "died":1,
    "rather":1,
    "405":1,
    "kim":1,
    "ye":1,
    "threatened":1,
    "selfish":1,
    "intents":1,
    "supposed":1,
    "bulletproof":1,
    "tints":1,
    "agents":1,
    "vocal":1,
    "flagrant":1,
    "smellin":1,
    "fragrance":1,
    "yeezys":1,
    "vans":1,
    "wouldntve":1,
    "popped":1,
    "xans":1,
    "fans":1,
    "writers":1,
    "block":1,
    "emcees":1,
    "cancel":1,
    "38":1,
    "8":1,
    "year":1,
    "wife":1,
    "6":1,
    "months":1,
    "maybach":1,
    "matted":1,
    "assistant":1,
    "backed":1,
    "slam":1,
    "dressing":1,
    "e":1,
    "rockin":1,
    "jewelry":1,
    "full":1,
    "disrespectful":1,
    "partys":1,
    "speed":1,
    "dropdropdropdrop":1,
    "robocop":1,
    "brace":1,
    "stomach":1,
    "pushin":1,
    "push":1,
    "sleep":1,
    "cousins":1,
    "grime":1,
    "filth":1,
    "story":1,
    "lifetime":1,
    "cheating":1,
    "stealing":1,
    "brother":1,
    "ggggood":1,
    "charlie":1,
    "accomplished":1,
    "lot":1,
    "numbers":1,
    "herzog":1,
    "drizzy":1,
    "c":1,
    "line":1,
    "stuck":1,
    "roots":1,
    "jimmy":1,
    "fallon":1,
    "dropped":1,
    "album":1,
    "platinum":1,
    "aggressive":1,
    "spazzin":1,
    "message":1,
    "overreckless":1,
    "odell":1,
    "beckham":1,
    "2020":1,
    "election":1,
    "yah":1,
    "trending":1,
    "couple":1,
    "appraised":1,
    "employees":1,
    "slaves":1,
    "lebron":1,
    "billi":1,
    "tenthousand":1,
    "shoppin":1,
    "wore":1,
    "designers":1,
    "wear":1,
    "arrogant":1,
    "pure":1,
    "grey":1,
    "poupon":1,
    "mustard":1,
    "poppin":1,
    "kimoji":1,
    "app":1,
    "cosby":1,
    "names":1,
    "harvey":1,
    "production":1,
    "needed":1,
    "infrastructure":1,
    "hottest":1,
    "discussion":1,
    "james":1,
    "harden":1,
    "swaggy":1,
    "p":1,
    "budget":1,
    "yoga":1,
    "flame":1,
    "jerk":1,
    "spouse":1,
    "rodeo":1,
    "pick":1,
    "thick":1,
    "mano":1,
    "twilite":1,
    "tone":1,
    "blessed":1,
    "truth":1,
    "celebrate":1,
    "awayayayay":1,
    "boat":1,
    "woah":1,
    "gone":1,
    "led":1,
    "world":1,
    "loving":2,
    "pray":2,
    "holy":2,
    "wrong":2,
    "fight":2,
    "hey":2,
    "field":2,
    "questions":2,
    "pain":2,
    "neck":2,
    "moving":2,
    "treat":2,
    "since":2,
    "coming":2,
    "follow":2,
    "candy":2,
    "job":2,
    "grammy":2,
    "else":2,
    "speak":2,
    "ride":2,
    "bet":2,
    "ex":2,
    "cannot":2,
    "lil":2,
    "everyone":2,
    "trust":2,
    "instigated":2,
    "relate":2,
    "asshole":2,
    "skin":2,
    "ay":2,
    "crashed":2,
    "people":2,
    "hollywood":2,
    "control":2,
    "road":2,
    "broke":2,
    "member":2,
    "broads":2,
    "atlanta":2,
    "twisting":2,
    "dope":2,
    "lean":2,
    "fanta":2,
    "credit":2,
    "cards":2,
    "scammers":2,
    "panda":2,
    "hundred":2,
    "hope":2,
    "understand":2,
    "asking":2,
    "stuff":2,
    "find":2,
    "rock":2,
    "seem":2,
    "hood":2,
    "school":2,
    "agent":2,
    "alive":2,
    "copped":2,
    "sky":2,
    "finger":2,
    "mother":2,
    "left":2,
    "nah":2,
    "low":2,
    "pay":2,
    "crazy":2,
    "south":2,
    "sider":2,
    "show":2,
    "another":2,
    "mixed":2,
    "j":2,
    "jay":2,
    "problems":2,
    "pac":2,
    "shot":2,
    "wait":2,
    "second":2,
    "ghetto":2,
    "tears":2,
    "myself":2,
    "anybody":2,
    "livin":2,
    "ray":2,
    "son":2,
    "city":2,
    "impregnate":2,
    "soon":2,
    "walkin":2,
    "believe":2,
    "rb":2,
    "motherfuckers":2,
    "dreams":2,
    "bring":2,
    "nice":2,
    "fucked":2,
    "shut":2,
    "living":2,
    "chop":2,
    "beats":2,
    "pink":2,
    "song":2,
    "":2,
    "feelings":2,
    "business":2,
    "children":2,
    "women":2,
    "thinking":2,
    "revealing":2,
    "four":2,
    "finna":2,
    "tribe":2,
    "honest":2,
    "issues":2,
    "cousin":2,
    "sad":2,
    "forgot":2,
    "thursday":2,
    "week":2,
    "tickets":2,
    "word":2,
    "throwed":2,
    "dawg":2,
    "plus":2,
    "fam":2,
    "pictures":2,
    "finished":2,
    "bill":2,
    "friend":2,
    "thinkin":2,
    "funny":2,
    "energy":2,
    "wheels":2,
    "spin":2,
    "next":2,
    "stole":2,
    "laptop":2,
    "paid":2,
    "dancin":2,
    "daddy":2,
    "cry":2,
    "burning":2,
    "trip":2,
    "mary":2,
    "club":2,
    "cover":2,
    "lambs":2,
    "wool":2,
    "surrounded":2,
    "wolves":2,
    "saint":2,
    "max":2,
    "b":2,
    "wavey":2,
    "loopy":2,
    "shoutout":2,
    "shout":2,
    "saw":2,
    "dollar":2,
    "happy":2,
    "gave":2,
    "picture":2,
    "movie":2,
    "ándale":2,
    "ei":2,
    "cam":2,
    "hotel":2,
    "class":2,
    "went":2,
    "service":2,
    "scary":2,
    "luxury":2,
    "list":2,
    "kids":2,
    "mulholland":2,
    "textin":2,
    "plans":2,
    "workin":2,
    "shoes":2,
    "turbo":2,
    "thots":2,
    "dirty":2,
    "perfect":2,
    "adidas":2,
    "run":2,
    "sonic":2,
    "dj":2,
    "runnin":2,
    "mamas":2,
    "watchin":2,
    "roll":2,
    "po":2,
    "deliver":3,
    "safe":3,
    "hell":3,
    "west":3,
    "gotta":3,
    "part":3,
    "little":3,
    "mine":3,
    "throw":3,
    "ugh":3,
    "home":3,
    "ever":3,
    "id":3,
    "hurt":3,
    "driving":3,
    "taking":3,
    "white":3,
    "whip":3,
    "try":3,
    "help":3,
    "wanting":3,
    "kanyes":3,
    "loved":3,
    "kin":3,
    "car":3,
    "jet":3,
    "fly":3,
    "eyes":3,
    "air":3,
    "act":3,
    "motherfucker":3,
    "taught":3,
    "boy":3,
    "jobs":3,
    "rich":3,
    "killed":3,
    "booty":3,
    "crying":3,
    "without":3,
    "thank":3,
    "new":3,
    "gettin":3,
    "rap":3,
    "drive":3,
    "party":3,
    "half":3,
    "side":3,
    "set":3,
    "theres":3,
    "somebody":3,
    "ooh":3,
    "layers":3,
    "ahead":3,
    "mention":3,
    "forget":3,
    "doin":3,
    "came":3,
    "place":3,
    "talked":3,
    "dirt":3,
    "pressure":3,
    "knew":3,
    "true":3,
    "flesh":3,
    "joseph":3,
    "unfollow":3,
    "unswallow":3,
    "nori":3,
    "game":3,
    "silver":3,
    "surfer":3,
    "years":3,
    "drove":3,
    "skrrt":3,
    "extra":3,
    "jammin":3,
    "dickll":3,
    "boom":3,
    "timbuck2":3,
    "looking":4,
    "somewhere":4,
    "war":4,
    "mean":4,
    "hard":4,
    "nobody":4,
    "late":4,
    "laugh":4,
    "father":4,
    "theyre":4,
    "enough":4,
    "times":4,
    "young":4,
    "babe":4,
    "unwanted":4,
    "imma":4,
    "worried":4,
    "ohhhhhhh":4,
    "miss":4,
    "called":4,
    "ask":4,
    "black":4,
    "phantom":4,
    "blame":4,
    "told":4,
    "mad":4,
    "put":4,
    "matter":4,
    "ey":4,
    "ayy":4,
    "sleeping":4,
    "snooze":4,
    "paper":4,
    "pablo":4,
    "cops":4,
    "steve":4,
    "really":4,
    "fur":4,
    "makin":4,
    "check":4,
    "fire":4,
    "thought":4,
    "lose":4,
    "waves":4,
    "crash":4,
    "moment":4,
    "text":4,
    "hoe":4,
    "deserve":4,
    "already":4,
    "took":4,
    "3":4,
    "pussy":4,
    "appreciate":4,
    "st":4,
    "30":4,
    "hours":4,
    "house":4,
    "days":4,
    "work":4,
    "jumped":4,
    "jumpman":4,
    "ah":4,
    "couches":4,
    "faith":5,
    "end":5,
    "take":5,
    "name":5,
    "hit":5,
    "daughter":5,
    "met":5,
    "lets":5,
    "feels":5,
    "beautiful":5,
    "something":5,
    "beat":5,
    "streets":5,
    "store":5,
    "hes":5,
    "feelin":5,
    "stop":5,
    "outta":5,
    "mind":5,
    "long":5,
    "lights":5,
    "well":5,
    "rah":5,
    "nothin":5,
    "hate":5,
    "around":5,
    "used":5,
    "minute":5,
    "louis":5,
    "drivin":5,
    "fade":5,
    "nike":5,
    "ultralight":6,
    "beam":6,
    "light":6,
    "head":6,
    "come":6,
    "til":6,
    "family":6,
    "going":6,
    "ass":6,
    "free":6,
    "give":6,
    "sorry":6,
    "power":6,
    "sun":6,
    "liberated":6,
    "talk":6,
    "problem":6,
    "x6":6,
    "round":6,
    "town":6,
    "girl":6,
    "wanted":6,
    "dick":6,
    "better":6,
    "start":6,
    "feeling":6,
    "middle":6,
    "play":6,
    "chicago":6,
    "hold":6,
    "big":6,
    "done":6,
    "open":6,
    "lord":6,
    "highlights":6,
    "equinox":6,
    "old":6,
    "wave":6,
    "remember":6,
    "whats":6,
    "guess":6,
    "turned":6,
    "corny":6,
    "million":6,
    "ha":6,
    "lifted":6,
    "everything":7,
    "night":7,
    "ima":7,
    "far":7,
    "soul":7,
    "hands":7,
    "might":7,
    "famous":7,
    "heard":7,
    "news":7,
    "call":7,
    "tryna":8,
    "keep":8,
    "damn":8,
    "first":8,
    "stacks":8,
    "best":8,
    "day":8,
    "last":8,
    "die":8,
    "dilla":8,
    "huh":8,
    "bout":8,
    "uh":8,
    "freak":8,
    "away":8,
    "please":8,
    "dream":9,
    "high":9,
    "way":9,
    "woo":9,
    "gon":9,
    "nothing":9,
    "em":9,
    "gonna":9,
    "think":9,
    "mama":9,
    "fuckin":9,
    "bitches":9,
    "wild":9,
    "thats":10,
    "look":10,
    "never":10,
    "said":10,
    "lost":10,
    "could":10,
    "though":10,
    "wish":10,
    "lie":10,
    "thing":11,
    "turn":11,
    "cause":11,
    "everybody":11,
    "say":11,
    "ive":11,
    "yes":11,
    "many":12,
    "yall":12,
    "would":12,
    "parties":12,
    "made":13,
    "still":13,
    "bad":13,
    "la":13,
    "us":14,
    "much":14,
    "friends":14,
    "wake":14,
    "whole":14,
    "always":14,
    "found":14,
    "morning":15,
    "money":15,
    "fadin":15,
    "yeah":16,
    "man":16,
    "niggas":16,
    "wanna":17,
    "go":17,
    "let":17,
    "every":17,
    "inside":17,
    "back":18,
    "real":18,
    "make":19,
    "fuck":19,
    "see":19,
    "bitch":19,
    "cant":20,
    "god":21,
    "one":21,
    "nigga":21,
    "even":21,
    "life":22,
    "want":23,
    "tell":23,
    "shit":23,
    "time":25,
    "baby":25,
    "good":26,
    "kanye":26,
    "got":26,
    "deep":26,
    "right":27,
    "love":29,
    "oh":30,
    "yeezy":30,
    "need":32,
    "aint":34,
    "no":45,
    "get":47,
    "feel":57,
    "know":58,
    "bam":73,
    "you":206,
    "i":381
 }